tgsender/__init__.py
tgsender/cli.py
tgsender/config.ini
tgsender/tgsender.py
tgsender/api/__init__.py
tgsender/api/api_tg.py
tgsender/api_async/__init__.py
tgsender/api_async/api_telegram.py
tgsender/mediainfo/__init__.py
tgsender/mediainfo/ffprobe_micro.py
tgsender/utils/__init__.py
tgsender/utils/time_out.py
tgsender/utils/utils.py
tgsender-0.1.12.dist-info/AUTHORS.rst
tgsender-0.1.12.dist-info/LICENSE
tgsender-0.1.12.dist-info/METADATA
tgsender-0.1.12.dist-info/WHEEL
tgsender-0.1.12.dist-info/entry_points.txt
tgsender-0.1.12.dist-info/top_level.txt
tgsender-0.1.12.dist-info/RECORD
