Metadata-Version: 2.1
Name: tgsender
Version: 0.1.12
Summary: An easy and automatic telegram uploader, with personalized descriptions.
Home-page: https://github.com/apenasrr/tgsender
Author: apenasrr
Author-email: apenasrr@gmail.com
License: MIT license
Keywords: tgsender
Classifier: Development Status :: 2 - Pre-Alpha
Classifier: Intended Audience :: Developers
Classifier: License :: OSI Approved :: MIT License
Classifier: Natural Language :: English
Classifier: Programming Language :: Python :: 3
Classifier: Programming Language :: Python :: 3.6
Classifier: Programming Language :: Python :: 3.7
Classifier: Programming Language :: Python :: 3.8
Requires-Python: >=3.6
License-File: LICENSE
License-File: AUTHORS.rst
Requires-Dist: Click >=7.0
Requires-Dist: asyncio
Requires-Dist: openpyxl
Requires-Dist: pyperclip
Requires-Dist: pandas
Requires-Dist: pyrofork
Requires-Dist: pyautogui
Requires-Dist: tgcrypto
Requires-Dist: natsort
Requires-Dist: unidecode
